.gitignore
CHANGES.txt
LICENSE.txt
README.txt
setup.py
js/__init__.py
js.raphael.egg-info/PKG-INFO
js.raphael.egg-info/SOURCES.txt
js.raphael.egg-info/dependency_links.txt
js.raphael.egg-info/entry_points.txt
js.raphael.egg-info/namespace_packages.txt
js.raphael.egg-info/not-zip-safe
js.raphael.egg-info/requires.txt
js.raphael.egg-info/top_level.txt
js/raphael/__init__.py
js/raphael/test_raphael.txt
js/raphael/resources/raphael-min.js
js/raphael/resources/raphael.js