Metadata-Version: 1.0
Name: js.raphael
Version: 2.1.0-1
Summary: Fanstatic packaging of Raphael
Home-page: https://github.com/disko/js.raphael
Author: Andreas Kaiser
Author-email: disko@binary-punks.com
License: BSD
Platform: UNKNOWN
